pyproject.toml
setup.cfg
setup.py
src/crosslab/soa_services/file/__init__.py
src/crosslab/soa_services/file/file_service.py
src/crosslab/soa_services/file/messages.py
src/crosslab/soa_services/file/py.typed
src/crosslab_soa_service_file.egg-info/PKG-INFO
src/crosslab_soa_service_file.egg-info/SOURCES.txt
src/crosslab_soa_service_file.egg-info/dependency_links.txt
src/crosslab_soa_service_file.egg-info/requires.txt
src/crosslab_soa_service_file.egg-info/top_level.txt
tests/test_standard.py